seedrecover/__init__.py
seedrecover/__main__.py
seedrecover/cli.py
seedrecover/english.txt
seedrecover/keyderiv.py
seedrecover/koios.py
seedrecover/order.py
seedrecover/stakecheck.py
seedrecover/wordlist.py
pyseedrecover-1.9.0.dist-info/entry_points.txt
pyseedrecover-1.9.0.dist-info/LICENSE
pyseedrecover-1.9.0.dist-info/WHEEL
pyseedrecover-1.9.0.dist-info/METADATA
pyseedrecover-1.9.0.dist-info/RECORD
