Metadata-Version: 2.1
Name: PySeedRecover
Version: 1.9.0
Summary: Recover Cardano seed phrases.
Author-email: Benjamin Braatz <bb@bbraatz.eu>
Classifier: Programming Language :: Python
Classifier: Programming Language :: Python :: 3 :: Only
Classifier: Programming Language :: Python :: 3.7
Classifier: Programming Language :: Python :: 3.10
Classifier: License :: OSI Approved :: MIT License
Classifier: Operating System :: OS Independent
Requires-Dist: ecpy
Project-URL: Home, https://github.com/HeptaSean/PySeedRecover
